viewtable/__init__.py
viewtable/cli.py
viewtable/h5pytools.py
viewtable-0.2.1.dist-info/DESCRIPTION.rst
viewtable-0.2.1.dist-info/METADATA
viewtable-0.2.1.dist-info/RECORD
viewtable-0.2.1.dist-info/WHEEL
viewtable-0.2.1.dist-info/entry_points.txt
viewtable-0.2.1.dist-info/metadata.json
viewtable-0.2.1.dist-info/top_level.txt
