Metadata-Version: 2.0
Name: viewtable
Version: 0.2.1
Summary: View tabularized version of input data.
Home-page: https://github.com/ecurtin2/python-view-table
Author: Evan M Curtin
Author-email: evanmcurtin@gmail.com
License: BSD
Platform: any
Classifier: Development Status :: 4 - Beta
Classifier: Environment :: Console
Classifier: Intended Audience :: Developers
Classifier: License :: OSI Approved :: MIT License
Classifier: Operating System :: POSIX
Classifier: Operating System :: MacOS
Classifier: Operating System :: Unix
Classifier: Operating System :: Microsoft :: Windows
Classifier: Programming Language :: Python
Classifier: Programming Language :: Python :: 3
Classifier: Topic :: Software Development :: Libraries :: Python Modules
Requires-Dist: click
Requires-Dist: pandas
Requires-Dist: h5py
